rock_cli/__init__.py
rock_cli/cli.py
rock_cli/globals.py
rock_cli/rocket.py
rock_cli/util.py
rock_cli-0.3.1.dist-info/DESCRIPTION.rst
rock_cli-0.3.1.dist-info/METADATA
rock_cli-0.3.1.dist-info/RECORD
rock_cli-0.3.1.dist-info/WHEEL
rock_cli-0.3.1.dist-info/entry_points.txt
rock_cli-0.3.1.dist-info/metadata.json
rock_cli-0.3.1.dist-info/top_level.txt
