Metadata-Version: 2.0
Name: rock-cli
Version: 0.3.1
Summary: A Rocketbank CLI
Home-page: https://github.com/iamale/rock
Author: Ale
Author-email: ale@songbee.net
License: UNKNOWN
Platform: UNKNOWN
Requires-Dist: Click (==6.4)
Requires-Dist: arequests (==0.1.0)
Requires-Dist: tabulate (==0.7.5)
Requires-Dist: yamlcfg (==0.5.3)
